{
  "minecraft:recipes/misc/leather": {
    "criteria": {
      "has_rabbit_hide": "2025-07-30 15:13:01 +0200"
    },
    "done": true
  },
  "minecraft:recipes/food/cooked_rabbit": {
    "criteria": {
      "has_rabbit": "2025-07-30 15:13:01 +0200"
    },
    "done": true
  },
  "minecraft:recipes/decorations/glow_item_frame": {
    "criteria": {
      "has_item_frame": "2025-07-30 15:11:45 +0200"
    },
    "done": true
  },
  "minecraft:recipes/decorations/crafting_table": {
    "criteria": {
      "unlock_right_away": "2025-07-30 15:11:11 +0200"
    },
    "done": true
  },
  "minecraft:recipes/food/cooked_rabbit_from_smoking": {
    "criteria": {
      "has_rabbit": "2025-07-30 15:13:01 +0200"
    },
    "done": true
  },
  "minecraft:recipes/food/cooked_rabbit_from_campfire_cooking": {
    "criteria": {
      "has_rabbit": "2025-07-30 15:13:01 +0200"
    },
    "done": true
  },
  "minecraft:adventure/root": {
    "criteria": {
      "killed_something": "2025-07-30 15:13:00 +0200"
    },
    "done": true
  },
  "minecraft:recipes/misc/yellow_dye_from_dandelion": {
    "criteria": {
      "has_dandelion": "2025-07-30 15:13:01 +0200"
    },
    "done": true
  },
  "minecraft:adventure/adventuring_time": {
    "criteria": {
      "minecraft:plains": "2025-07-30 15:11:12 +0200"
    },
    "done": false
  },
  "DataVersion": 3465
}